blocks/__init__.py
blocks/annotations.py
blocks/app.py
blocks/compat.py
blocks/decorators.py
blocks/graph.py
blocks/ioc.py
blocks/logger.py
blocks/metric_collector.py
blocks/py.typed
blocks/runners.py
blocks/validation.py
blocks/visualization.py
blocks/db/__init__.py
blocks/db/types.py
blocks/db/next/__init__.py
blocks/db/next/sql.py
blocks/db/next/types.py
blocks/db/sql/__init__.py
blocks/db/sql/processors.py
blocks/db/sql/sources.py
blocks/hive/__init__.py
blocks/hive/processors.py
blocks/hive/sources.py
blocks/kafka/__init__.py
blocks/kafka/app.py
blocks/kafka/events.py
blocks/kafka/processors.py
blocks/kafka/sources.py
blocks/kafka/topics.py
blocks/kafka/types.py
blocks/mssql/__init__.py
blocks/mssql/app.py
blocks/mssql/next.py
blocks/mssql/processors.py
blocks/mssql/protocols.py
blocks/mssql/sources.py
blocks/postgres/__init__.py
blocks/postgres/app.py
blocks/postgres/next.py
blocks/postgres/processors.py
blocks/postgres/protocols.py
blocks/postgres/sources.py
blocks/processors/__init__.py
blocks/processors/batcher.py
blocks/redis/__init__.py
blocks/redis/app.py
blocks/redis/events.py
blocks/redis/processors.py
blocks/redis/serdes.py
blocks/redis/sources.py
blocks/redis/streams.py
blocks/sources/__init__.py
blocks/sources/schedule.py
blocks/sqlite/__init__.py
blocks/types/__init__.py
blocks/types/base.py
blocks/types/graph.py
blocks/types/ioc.py
blocks/types/metrics.py
blocks/types/multiprocess.py
typed_blocks-0.18.2.dist-info/LICENSE
typed_blocks-0.18.2.dist-info/METADATA
typed_blocks-0.18.2.dist-info/WHEEL
typed_blocks-0.18.2.dist-info/top_level.txt
typed_blocks-0.18.2.dist-info/RECORD
