Metadata-Version: 2.1
Name: typed-blocks
Version: 0.18.2
Summary: Modular event-centric python library made for simplification typical stream applications development with python type system strong exploitation.
Home-page: https://github.com/severstal-digital/typed-blocks
Author: Daniil Zubakin
Author-email: <daniilzubakin@gmail.com>
License: Apache-2.0 License
Project-URL: Bug Tracker, https://github.com/severstal-digital/typed-blocks/issues
Classifier: Development Status :: 4 - Beta
Classifier: Programming Language :: Python :: 3
Classifier: Programming Language :: Python :: 3 :: Only
Classifier: License :: OSI Approved :: Apache Software License
Classifier: Operating System :: POSIX :: Linux
Classifier: Intended Audience :: Developers
Classifier: Topic :: Software Development :: Libraries :: Python Modules
Requires-Python: >=3.9
License-File: LICENSE
Provides-Extra: full
Requires-Dist: wunderkafka ; extra == 'full'
Requires-Dist: schedule >=1.1.0 ; extra == 'full'
Requires-Dist: redis >=4.0.2 ; extra == 'full'
Requires-Dist: types-redis >=4.0.2 ; extra == 'full'
Requires-Dist: psycopg2-binary >=2.9.2 ; extra == 'full'
Requires-Dist: networkx >=2.6.3 ; extra == 'full'
Requires-Dist: matplotlib >=3.5.1 ; extra == 'full'
Requires-Dist: graphviz >=0.20.1 ; extra == 'full'
Requires-Dist: dill >=0.3.6 ; extra == 'full'
Requires-Dist: PyHive >=0.6.5 ; extra == 'full'
Requires-Dist: thrift >=0.16.0 ; extra == 'full'
Requires-Dist: thrift-sasl >=0.4.3 ; extra == 'full'
Requires-Dist: sasl >=0.3.1 ; extra == 'full'
Requires-Dist: pymssql >=2.2.6 ; extra == 'full'
Provides-Extra: graphviz
Requires-Dist: graphviz >=0.20.1 ; extra == 'graphviz'
Requires-Dist: networkx >=2.6.3 ; extra == 'graphviz'
Requires-Dist: matplotlib >=3.5.1 ; extra == 'graphviz'
Provides-Extra: hive
Requires-Dist: PyHive >=0.6.5 ; extra == 'hive'
Requires-Dist: thrift >=0.16.0 ; extra == 'hive'
Requires-Dist: thrift-sasl >=0.4.3 ; extra == 'hive'
Requires-Dist: sasl >=0.3.1 ; extra == 'hive'
Provides-Extra: kafka
Requires-Dist: wunderkafka ; extra == 'kafka'
Provides-Extra: mssql
Requires-Dist: pymssql >=2.2.6 ; extra == 'mssql'
Provides-Extra: parallel
Requires-Dist: dill >=0.3.6 ; extra == 'parallel'
Provides-Extra: postgres
Requires-Dist: psycopg2-binary >=2.9.2 ; extra == 'postgres'
Provides-Extra: redis
Requires-Dist: redis >=4.0.2 ; extra == 'redis'
Requires-Dist: types-redis >=4.0.2 ; extra == 'redis'
Provides-Extra: schedule
Requires-Dist: schedule >=1.1.0 ; extra == 'schedule'
Provides-Extra: visualization
Requires-Dist: networkx >=2.6.3 ; extra == 'visualization'
Requires-Dist: matplotlib >=3.5.1 ; extra == 'visualization'
